TlvParser/TlvParser.py
TlvParser/__init__.py
tlv_for_everyone-0.1.0.dist-info/licenses/LICENSE
tlv_for_everyone-0.1.0.dist-info/METADATA
tlv_for_everyone-0.1.0.dist-info/WHEEL
tlv_for_everyone-0.1.0.dist-info/top_level.txt
tlv_for_everyone-0.1.0.dist-info/RECORD
