Metadata-Version: 2.4
Name: tlv-for-everyone
Version: 0.1.0
Summary: Python BER-TLV parser/encoder for EMV & smartcard data
Author-email: Vitalij Gotovskij <vitalij@cdeveloper.eu>
License-Expression: MIT
Project-URL: Homepage, https://github.com/yourname/tlv-for-everyone
Project-URL: Issues, https://github.com/yourname/tlv-for-everyone/issues
Keywords: TLV,BER,EMV,smartcard,parser,APDU
Classifier: Development Status :: 3 - Alpha
Classifier: Intended Audience :: Developers
Classifier: Operating System :: OS Independent
Classifier: Programming Language :: Python :: 3
Classifier: Programming Language :: Python :: 3.8
Classifier: Programming Language :: Python :: 3.9
Classifier: Programming Language :: Python :: 3.10
Classifier: Programming Language :: Python :: 3.11
Classifier: Programming Language :: Python :: 3.12
Classifier: Topic :: Software Development :: Libraries
Classifier: Topic :: Security :: Cryptography
Requires-Python: >=3.8
License-File: LICENSE
Dynamic: license-file
